Metadata-Version: 2.1
Name: skadoosh
Version: 0.0.1
Summary: Skadoosh python package
Author: Nguyen Trieu
Author-email: tdnguyen.uet@gmail.com
License-File: LICENSE
